jnbv-2024.12.10.dist-info/METADATA
jnbv-2024.12.10.dist-info/WHEEL
jnbv-2024.12.10.dist-info/entry_points.txt
jnbv-2024.12.10.dist-info/licenses/LICENSE
jnbv/__init__.py
jnbv/__main__.py
jnbv/compare.py
jnbv/execute.py
jnbv/read.py
jnbv/test.py
jnbv/utils.py
jnbv-2024.12.10.dist-info/RECORD
