Metadata-Version: 2.1
Name: jnbv
Version: 2024.12.10
Summary: Validation of Jupyter notebooks and kernels
Keywords: jupyter
Author-Email: Jason Brudvik <jason.brudvik@maxiv.lu.se>
License: BSD 2-Clause License
Classifier: Development Status :: 4 - Beta
Classifier: Intended Audience :: Developers
Classifier: Topic :: Scientific/Engineering :: Physics
Classifier: License :: OSI Approved :: BSD License
Classifier: Programming Language :: Python :: 3
Classifier: Programming Language :: Python :: 3.8
Classifier: Programming Language :: Python :: 3.9
Classifier: Programming Language :: Python :: 3.10
Classifier: Programming Language :: Python :: 3.11
Classifier: Programming Language :: Python :: 3.12
Project-URL: Homepage, https://gitlab.com/MAXIV-SCISW/JUPYTERHUB/jnbv
Project-URL: Documentation, https://gitlab.com/MAXIV-SCISW/JUPYTERHUB/jnbv/-/blob/master/README.md
Project-URL: Repository, https://gitlab.com/MAXIV-SCISW/JUPYTERHUB/jnbv
Project-URL: Issues, https://gitlab.com/MAXIV-SCISW/JUPYTERHUB/jnbv/-/issues
Project-URL: Changelog, https://gitlab.com/MAXIV-SCISW/JUPYTERHUB/jnbv/-/blob/master/CHANGELOG.md
Requires-Python: <3.13,>=3.8
Requires-Dist: papermill
Requires-Dist: nbformat
Requires-Dist: jupyter
Requires-Dist: envkernel
Requires-Dist: ipykernel
